<?xml version="1.0" encoding="utf-8" ?>
<data>
	<top name="unit4">Unit 4</top>
	<mod title="本模块为课后同步练习，请在光盘配套的纸质手册上完成。&#x000A;"></mod>
	<items id="1" title="Part A&#x000A;I. 将下列单词写在相应的图片下。" type="ROW" column="1">
		<item id="1.">study</item>
		<item id="2.">table</item>
		<item id="3.">sofa</item>
		<item id="4.">fridge</item>
		<item id="5.">bedroom</item>
		<item id="6.">bathroom</item>
		<item id="7.">bed</item>
		<item id="8.">phone</item>
	</items>
	<items id="2" title="II. 连词成句，注意大小写及标点符号。" type="ROW" column="1">
		<item id="1.">Where is the study?</item>
		<item id="2.">Is she in the living room?</item>
		<item id="3.">Go to the bathroom. Take a shower. </item>
		<item id="4.">I have a cat. She is cute.</item>
		<item id="5.">She is in the bedroom.</item>
	</items>
	<items id="3" title="Part B&#x000A;II. 中英文连线。" type="ROW" column="5">
		<item id="1." >D</item>
		<item id="2." >A</item>
		<item id="3." >B</item>
		<item id="4." >C</item>
		<item id="5." >E</item>
	</items>
	<items id="4" title="III. 情境问答。" type="ROW" column="5">
		<item id="1." >A</item>
		<item id="2." >B</item>
		<item id="3." >A</item>
		<item id="4." >A</item>
		<item id="5." >B</item>
	</items>
	<items id="5" title="Part C&#x000A;I. 找一找，圈一圈。" type="ROW" column="1">
		<item id="1.">find</item>
		<item id="2.">living</item>
		<item id="3.">study</item>
		<item id="4.">them</item>
		<item id="5.">phone</item>
	</items>
	<items id="6" title="II. 选择与图片相符的单词。" type="ROW"  column="5"> 
		<item id="1.">A</item>
		<item id="2.">A</item>
		<item id="3.">B</item>
		<item id="4.">B</item>
		<item id="5.">A</item>
	</items>
	<items id="7" title="III. 判断对错，对的打“√”，错的打“×”。" type="ROW" column="4">
		<item id="1." >×</item>
		<item id="2." >√</item>
		<item id="3." >×</item>
		<item id="4." >√</item>
	</items>
</data>